README.md
setup.py
sub_parser/__init__.py
sub_parser/utils.py
sub_parser/ss/__init__.py
sub_parser/ss/parser.py
sub_parser/ssr/__init__.py
sub_parser/ssr/parser.py
subscription_parser.egg-info/PKG-INFO
subscription_parser.egg-info/SOURCES.txt
subscription_parser.egg-info/dependency_links.txt
subscription_parser.egg-info/requires.txt
subscription_parser.egg-info/top_level.txt