Metadata-Version: 1.0
Name: subscription-parser
Version: 0.1
Summary: A python package to parse SS/SSR subscription link
Home-page: http://https://github.com/0KABE/subscription-parser
Author: 0KABE
Author-email: RIN.OKAB3@GMAIL.COM
License: MIT
Platform: UNKNOWN
